{"50587707956@s.whatsapp.net":true,"50662208275@s.whatsapp.net":true,"50662694778@s.whatsapp.net":true,"50663019393@s.whatsapp.net":true,"50663138444@s.whatsapp.net":true,"50664859628@s.whatsapp.net":true,"50671541516@s.whatsapp.net":true,"50671697291@s.whatsapp.net":true,"50672607438@s.whatsapp.net":true,"50672607438:55@s.whatsapp.net":true,"50684670302@s.whatsapp.net":true,"50684907218@s.whatsapp.net":true,"50684907218:15@s.whatsapp.net":true,"50687311791@s.whatsapp.net":true,"50687968364@s.whatsapp.net":true,"5491122378664@s.whatsapp.net":true}